[
  {
    "title": "Engine",
    "icon": "fas fa-engine",
    "items": [
      { "label": "Type", "value": "Honda B18CR" },
      { "label": "Displacement", "value": "1.8L (1,797 cc)" },
      { "label": "Power Output", "value": "132.5kw" },
      { "label": "Torque", "value": "--- Nm" },
      { "label": "Redline", "value": "8720 RPM" }
    ]
  },
  {
    "title": "Transmission",
    "icon": "fas fa-cog",
    "items": [
      { "label": "Type", "value": "Type R - S80 LSD" },
      { "label": "Clutch", "value": "Standard Exedy" },
      { "label": "Differential", "value": "Cusco LSD Type RS 1.5Way" },
      { "label": "Gear Ratios", "value": "1/2 - OEM  ||  3/4/5 - GearX Short ratio  ||  FD - OEM" },
      { "label": "Shifter", "value": "FastLine Shifter - Honed Gear Linkage - HR Detent Springs" }
    ]
  },
  {
    "title": "Suspension",
    "icon": "fas fa-tools",
    "items": [
      { "label": "Coilovers", "value": "BC ER - F: 20kg | R: 14kg" },
      { "label": "Suspension", "value": "Double Wishbone" },
      { "label": "Camber Arms", "value": "F: Skunk2 | R: Honed Developments" },
      { "label": "Geometry", "value": "Full Honed Geometry correction kit" },
      { "label": "Castor", "value": "Innovative Traction Bar" }
    ]
  },
  {
    "title": "Brakes",
    "icon": "fas fa-tachometer-alt",
    "items": [
      { "label": "Calipers", "value": "F: DC2R/CRV 282mm | R: Stock CRX" },
      { "label": "Rotors", "value": "F: DBA T3 282mm | R: Stock CRX Blanks" },
      { "label": "Brake Pads", "value": "F: Intima RR | R: Intima SS" },
      { "label": "Brake Fluid", "value": "Motul RBF 600" },
      { "label": "Brake Lines", "value": "HEL Braided Lines" },
      { "label": "Brake Assist", "value": "Honed Brake Booster Delete" }
    ]
  },
  {
    "title": "Interior",
    "icon": "fas fa-car",
    "items": [
      { "label": "Seat", "value": "Racetech - RT4009HR" },
      { "label": "Harness", "value": "RPM 6pt 3inch" },
      { "label": "Steering Wheel", "value": "Sabelt SW-733 Flat Bottom" },
      { "label": "Data Aquition", "value": "WillTech - Race Dash" }
    ]
  },
  {
    "title": "Exterior",
    "icon": "fas fa-wind",
    "items": [
      { "label": "Test", "value": "---" },
      { "label": "Test", "value": "---" },
      { "label": "Test", "value": "---" },
      { "label": "Test", "value": "---" },
      { "label": "Test", "value": "---" }
    ]
  }
]
